{
    "sourceFile": "mvc/app/views/laptop/editLaptop.blade.php",
    "activeCommit": 0,
    "commits": [
        {
            "activePatchIndex": 14,
            "patches": [
                {
                    "date": 1656049696833,
                    "content": "Index: \n===================================================================\n--- \n+++ \n"
                },
                {
                    "date": 1656049711835,
                    "content": "Index: \n===================================================================\n--- \n+++ \n@@ -10,30 +10,30 @@\n             <div class=\"card-body\">\r\n                 <form method=\"post\" enctype=\"multipart/form-data\">\r\n                     <div class=\"form-group\">\r\n                         <label for=\"\">Name</label>\r\n-                        <input type=\"text\" name=\"name\" class=\"form-control\" value=\"{{$passengers->name}}\">\r\n+                        <input type=\"text\" name=\"name\" class=\"form-control\" value=\"{{$laptops->name}}\">\r\n                     </div>\r\n                     <div class=\"form-group\">\r\n                         <label for=\"\">Train_id</label>\r\n-                        <input type=\"text\" name=\"name\" class=\"form-control\" value=\"{{$passengers->train_id}}\">\r\n+                        <input type=\"text\" name=\"name\" class=\"form-control\" value=\"{{$laptops->train_id}}\">\r\n                     </div>\r\n                     <div class=\"form-group\">\r\n                             <div class=\"row\">\r\n                                 <div class=\"col-6 offset-3\">\r\n-                                    <img src=\"{{BASE_URL . $passengers->avatar}}\" class=\"img-thumbnail\">\r\n+                                    <img src=\"{{BASE_URL . $laptops->avatar}}\" class=\"img-thumbnail\">\r\n                                 </div>\r\n                             </div>\r\n                             <label for=\"\">Avatar</label>\r\n                             <input type=\"file\" name=\"avatar\" class=\"form-control\">\r\n                     </div>\r\n                     <div class=\"form-group\">\r\n                         <label for=\"\">Gender</label>\r\n-                        <input type=\"text\" name=\"gender\" class=\"form-control\" value=\"{{$passengers->gender}}\">\r\n+                        <input type=\"text\" name=\"gender\" class=\"form-control\" value=\"{{$laptops->gender}}\">\r\n                     </div>\r\n                     <div class=\"form-group\">\r\n                         <label for=\"\">Phone</label>\r\n-                        <input type=\"number\" name=\"phone\" class=\"form-control\" value=\"{{$passengers->phone}}\">\r\n+                        <input type=\"number\" name=\"phone\" class=\"form-control\" value=\"{{$laptops->phone}}\">\r\n                     </div>\r\n                     <div class=\"text-right\">\r\n                         <button type=\"submit\" class=\"btn btn-sm btn-primary\">Sửa Vé Tàu</button>\r\n                     </div>\r\n"
                },
                {
                    "date": 1656049745503,
                    "content": "Index: \n===================================================================\n--- \n+++ \n@@ -13,9 +13,9 @@\n                         <label for=\"\">Name</label>\r\n                         <input type=\"text\" name=\"name\" class=\"form-control\" value=\"{{$laptops->name}}\">\r\n                     </div>\r\n                     <div class=\"form-group\">\r\n-                        <label for=\"\">Train_id</label>\r\n+                        <label for=\"\">Brand_id_id</label>\r\n                         <input type=\"text\" name=\"name\" class=\"form-control\" value=\"{{$laptops->train_id}}\">\r\n                     </div>\r\n                     <div class=\"form-group\">\r\n                             <div class=\"row\">\r\n"
                },
                {
                    "date": 1656049762443,
                    "content": "Index: \n===================================================================\n--- \n+++ \n@@ -13,10 +13,10 @@\n                         <label for=\"\">Name</label>\r\n                         <input type=\"text\" name=\"name\" class=\"form-control\" value=\"{{$laptops->name}}\">\r\n                     </div>\r\n                     <div class=\"form-group\">\r\n-                        <label for=\"\">Brand_id_id</label>\r\n-                        <input type=\"text\" name=\"name\" class=\"form-control\" value=\"{{$laptops->train_id}}\">\r\n+                        <label for=\"\">Brand_id</label>\r\n+                        <input type=\"text\" name=\"name\" class=\"form-control\" value=\"{{$laptops->brand_id}}\">\r\n                     </div>\r\n                     <div class=\"form-group\">\r\n                             <div class=\"row\">\r\n                                 <div class=\"col-6 offset-3\">\r\n"
                },
                {
                    "date": 1656049767996,
                    "content": "Index: \n===================================================================\n--- \n+++ \n@@ -19,9 +19,9 @@\n                     </div>\r\n                     <div class=\"form-group\">\r\n                             <div class=\"row\">\r\n                                 <div class=\"col-6 offset-3\">\r\n-                                    <img src=\"{{BASE_URL . $laptops->avatar}}\" class=\"img-thumbnail\">\r\n+                                    <img src=\"{{BASE_URL . $laptops->image}}\" class=\"img-thumbnail\">\r\n                                 </div>\r\n                             </div>\r\n                             <label for=\"\">Avatar</label>\r\n                             <input type=\"file\" name=\"avatar\" class=\"form-control\">\r\n"
                },
                {
                    "date": 1656049780765,
                    "content": "Index: \n===================================================================\n--- \n+++ \n@@ -14,17 +14,17 @@\n                         <input type=\"text\" name=\"name\" class=\"form-control\" value=\"{{$laptops->name}}\">\r\n                     </div>\r\n                     <div class=\"form-group\">\r\n                         <label for=\"\">Brand_id</label>\r\n-                        <input type=\"text\" name=\"name\" class=\"form-control\" value=\"{{$laptops->brand_id}}\">\r\n+                        <input type=\"text\" name=\"brand\" class=\"form-control\" value=\"{{$laptops->brand_id}}\">\r\n                     </div>\r\n                     <div class=\"form-group\">\r\n                             <div class=\"row\">\r\n                                 <div class=\"col-6 offset-3\">\r\n                                     <img src=\"{{BASE_URL . $laptops->image}}\" class=\"img-thumbnail\">\r\n                                 </div>\r\n                             </div>\r\n-                            <label for=\"\">Avatar</label>\r\n+                            <label for=\"\">Image</label>\r\n                             <input type=\"file\" name=\"avatar\" class=\"form-control\">\r\n                     </div>\r\n                     <div class=\"form-group\">\r\n                         <label for=\"\">Gender</label>\r\n"
                },
                {
                    "date": 1656049788077,
                    "content": "Index: \n===================================================================\n--- \n+++ \n@@ -14,18 +14,18 @@\n                         <input type=\"text\" name=\"name\" class=\"form-control\" value=\"{{$laptops->name}}\">\r\n                     </div>\r\n                     <div class=\"form-group\">\r\n                         <label for=\"\">Brand_id</label>\r\n-                        <input type=\"text\" name=\"brand\" class=\"form-control\" value=\"{{$laptops->brand_id}}\">\r\n+                        <input type=\"text\" name=\"brand_id\" class=\"form-control\" value=\"{{$laptops->brand_id}}\">\r\n                     </div>\r\n                     <div class=\"form-group\">\r\n                             <div class=\"row\">\r\n                                 <div class=\"col-6 offset-3\">\r\n                                     <img src=\"{{BASE_URL . $laptops->image}}\" class=\"img-thumbnail\">\r\n                                 </div>\r\n                             </div>\r\n                             <label for=\"\">Image</label>\r\n-                            <input type=\"file\" name=\"avatar\" class=\"form-control\">\r\n+                            <input type=\"file\" name=\"image\" class=\"form-control\">\r\n                     </div>\r\n                     <div class=\"form-group\">\r\n                         <label for=\"\">Gender</label>\r\n                         <input type=\"text\" name=\"gender\" class=\"form-control\" value=\"{{$laptops->gender}}\">\r\n"
                },
                {
                    "date": 1656049794378,
                    "content": "Index: \n===================================================================\n--- \n+++ \n@@ -26,9 +26,9 @@\n                             <label for=\"\">Image</label>\r\n                             <input type=\"file\" name=\"image\" class=\"form-control\">\r\n                     </div>\r\n                     <div class=\"form-group\">\r\n-                        <label for=\"\">Gender</label>\r\n+                        <label for=\"\">Detail</label>\r\n                         <input type=\"text\" name=\"gender\" class=\"form-control\" value=\"{{$laptops->gender}}\">\r\n                     </div>\r\n                     <div class=\"form-group\">\r\n                         <label for=\"\">Phone</label>\r\n"
                },
                {
                    "date": 1656049807791,
                    "content": "Index: \n===================================================================\n--- \n+++ \n@@ -27,9 +27,9 @@\n                             <input type=\"file\" name=\"image\" class=\"form-control\">\r\n                     </div>\r\n                     <div class=\"form-group\">\r\n                         <label for=\"\">Detail</label>\r\n-                        <input type=\"text\" name=\"gender\" class=\"form-control\" value=\"{{$laptops->gender}}\">\r\n+                        <input type=\"text\" name=\"detail\" class=\"form-control\" value=\"{{$laptops->gender}}\">\r\n                     </div>\r\n                     <div class=\"form-group\">\r\n                         <label for=\"\">Phone</label>\r\n                         <input type=\"number\" name=\"phone\" class=\"form-control\" value=\"{{$laptops->phone}}\">\r\n"
                },
                {
                    "date": 1656049818642,
                    "content": "Index: \n===================================================================\n--- \n+++ \n@@ -27,12 +27,12 @@\n                             <input type=\"file\" name=\"image\" class=\"form-control\">\r\n                     </div>\r\n                     <div class=\"form-group\">\r\n                         <label for=\"\">Detail</label>\r\n-                        <input type=\"text\" name=\"detail\" class=\"form-control\" value=\"{{$laptops->gender}}\">\r\n+                        <input type=\"text\" name=\"detail\" class=\"form-control\" value=\"{{$laptops->detail}}\">\r\n                     </div>\r\n                     <div class=\"form-group\">\r\n-                        <label for=\"\">Phone</label>\r\n+                        <label for=\"\">Price</label>\r\n                         <input type=\"number\" name=\"phone\" class=\"form-control\" value=\"{{$laptops->phone}}\">\r\n                     </div>\r\n                     <div class=\"text-right\">\r\n                         <button type=\"submit\" class=\"btn btn-sm btn-primary\">Sửa Vé Tàu</button>\r\n"
                },
                {
                    "date": 1656049826717,
                    "content": "Index: \n===================================================================\n--- \n+++ \n@@ -31,9 +31,9 @@\n                         <input type=\"text\" name=\"detail\" class=\"form-control\" value=\"{{$laptops->detail}}\">\r\n                     </div>\r\n                     <div class=\"form-group\">\r\n                         <label for=\"\">Price</label>\r\n-                        <input type=\"number\" name=\"phone\" class=\"form-control\" value=\"{{$laptops->phone}}\">\r\n+                        <input type=\"number\" name=\"price\" class=\"form-control\" value=\"{{$laptops->price}}\">\r\n                     </div>\r\n                     <div class=\"text-right\">\r\n                         <button type=\"submit\" class=\"btn btn-sm btn-primary\">Sửa Vé Tàu</button>\r\n                     </div>\r\n"
                },
                {
                    "date": 1656049832087,
                    "content": "Index: \n===================================================================\n--- \n+++ \n@@ -34,9 +34,9 @@\n                         <label for=\"\">Price</label>\r\n                         <input type=\"number\" name=\"price\" class=\"form-control\" value=\"{{$laptops->price}}\">\r\n                     </div>\r\n                     <div class=\"text-right\">\r\n-                        <button type=\"submit\" class=\"btn btn-sm btn-primary\">Sửa Vé Tàu</button>\r\n+                        <button type=\"submit\" class=\"btn btn-sm btn-primary\">Sửa Laptop</button>\r\n                     </div>\r\n                 </form>\r\n             </div>\r\n         </div>\r\n"
                },
                {
                    "date": 1656051272640,
                    "content": "Index: \n===================================================================\n--- \n+++ \n@@ -4,9 +4,9 @@\n <div class=\"row\">\r\n     <div class=\"col-md-6 offset-md-3\">\r\n         <div class=\"card\">\r\n             <div class=\"card-header\">\r\n-                <h3 class=\"card-title\">Sửa Vé Tàu</h3>\r\n+                <h3 class=\"card-title\">Sửa Lap</h3>\r\n             </div>\r\n             <div class=\"card-body\">\r\n                 <form method=\"post\" enctype=\"multipart/form-data\">\r\n                     <div class=\"form-group\">\r\n"
                },
                {
                    "date": 1656051489425,
                    "content": "Index: \n===================================================================\n--- \n+++ \n@@ -13,12 +13,8 @@\n                         <label for=\"\">Name</label>\r\n                         <input type=\"text\" name=\"name\" class=\"form-control\" value=\"{{$laptops->name}}\">\r\n                     </div>\r\n                     <div class=\"form-group\">\r\n-                        <label for=\"\">Brand_id</label>\r\n-                        <input type=\"text\" name=\"brand_id\" class=\"form-control\" value=\"{{$laptops->brand_id}}\">\r\n-                    </div>\r\n-                    <div class=\"form-group\">\r\n                             <div class=\"row\">\r\n                                 <div class=\"col-6 offset-3\">\r\n                                     <img src=\"{{BASE_URL . $laptops->image}}\" class=\"img-thumbnail\">\r\n                                 </div>\r\n"
                },
                {
                    "date": 1656051513432,
                    "content": "Index: \n===================================================================\n--- \n+++ \n@@ -13,8 +13,12 @@\n                         <label for=\"\">Name</label>\r\n                         <input type=\"text\" name=\"name\" class=\"form-control\" value=\"{{$laptops->name}}\">\r\n                     </div>\r\n                     <div class=\"form-group\">\r\n+                        <label for=\"\">Brand_id</label>\r\n+                        <input type=\"text\" name=\"brand_id\" class=\"form-control\" value=\"{{$laptops->brand_id}}\">\r\n+                    </div>\r\n+                    <div class=\"form-group\">\r\n                             <div class=\"row\">\r\n                                 <div class=\"col-6 offset-3\">\r\n                                     <img src=\"{{BASE_URL . $laptops->image}}\" class=\"img-thumbnail\">\r\n                                 </div>\r\n"
                }
            ],
            "date": 1656049696833,
            "name": "Commit-0",
            "content": "@extends('layouts.main')\r\n@section('title', \"Sửa Chuyến Tàu\")\r\n@section('content')\r\n<div class=\"row\">\r\n    <div class=\"col-md-6 offset-md-3\">\r\n        <div class=\"card\">\r\n            <div class=\"card-header\">\r\n                <h3 class=\"card-title\">Sửa Vé Tàu</h3>\r\n            </div>\r\n            <div class=\"card-body\">\r\n                <form method=\"post\" enctype=\"multipart/form-data\">\r\n                    <div class=\"form-group\">\r\n                        <label for=\"\">Name</label>\r\n                        <input type=\"text\" name=\"name\" class=\"form-control\" value=\"{{$passengers->name}}\">\r\n                    </div>\r\n                    <div class=\"form-group\">\r\n                        <label for=\"\">Train_id</label>\r\n                        <input type=\"text\" name=\"name\" class=\"form-control\" value=\"{{$passengers->train_id}}\">\r\n                    </div>\r\n                    <div class=\"form-group\">\r\n                            <div class=\"row\">\r\n                                <div class=\"col-6 offset-3\">\r\n                                    <img src=\"{{BASE_URL . $passengers->avatar}}\" class=\"img-thumbnail\">\r\n                                </div>\r\n                            </div>\r\n                            <label for=\"\">Avatar</label>\r\n                            <input type=\"file\" name=\"avatar\" class=\"form-control\">\r\n                    </div>\r\n                    <div class=\"form-group\">\r\n                        <label for=\"\">Gender</label>\r\n                        <input type=\"text\" name=\"gender\" class=\"form-control\" value=\"{{$passengers->gender}}\">\r\n                    </div>\r\n                    <div class=\"form-group\">\r\n                        <label for=\"\">Phone</label>\r\n                        <input type=\"number\" name=\"phone\" class=\"form-control\" value=\"{{$passengers->phone}}\">\r\n                    </div>\r\n                    <div class=\"text-right\">\r\n                        <button type=\"submit\" class=\"btn btn-sm btn-primary\">Sửa Vé Tàu</button>\r\n                    </div>\r\n                </form>\r\n            </div>\r\n        </div>\r\n    </div>\r\n</div>\r\n@endsection"
        }
    ]
}